<?xml version="1.0" ?>
<FlowMonitor>
  <FlowStats>
    <Flow flowId="1" timeFirstTxPacket="+0.0ns" timeFirstRxPacket="+232467.0ns" timeLastTxPacket="+88000002.0ns" timeLastRxPacket="+92256499.0ns" delaySum="+21828043.0ns" jitterSum="+4152288.0ns" lastDelay="+4256497.0ns" txBytes="5432" rxBytes="5432" txPackets="7" rxPackets="7" lostPackets="0" timesForwarded="14">
      <delayHistogram nBins="5" >
        <bin index="0" start="0" width="0.001" count="2" />
        <bin index="4" start="0.004" width="0.001" count="5" />
      </delayHistogram>
      <jitterHistogram nBins="5" >
        <bin index="0" start="0" width="0.001" count="5" />
        <bin index="4" start="0.004" width="0.001" count="1" />
      </jitterHistogram>
      <packetSizeHistogram nBins="54" >
        <bin index="2" start="40" width="20" count="1" />
        <bin index="3" start="60" width="20" count="1" />
        <bin index="53" start="1060" width="20" count="5" />
      </packetSizeHistogram>
      <flowInterruptionsHistogram nBins="0" >
      </flowInterruptionsHistogram>
    </Flow>
    <Flow flowId="2" timeFirstTxPacket="+232467.0ns" timeFirstRxPacket="+464934.0ns" timeLastTxPacket="+92256499.0ns" timeLastRxPacket="+92456902.0ns" delaySum="+2781441.0ns" jitterSum="+673068.0ns" lastDelay="+200403.0ns" txBytes="656" rxBytes="656" txPackets="11" rxPackets="11" lostPackets="0" timesForwarded="22">
      <delayHistogram nBins="1" >
        <bin index="0" start="0" width="0.001" count="11" />
      </delayHistogram>
      <jitterHistogram nBins="1" >
        <bin index="0" start="0" width="0.001" count="10" />
      </jitterHistogram>
      <packetSizeHistogram nBins="4" >
        <bin index="2" start="40" width="20" count="6" />
        <bin index="3" start="60" width="20" count="5" />
      </packetSizeHistogram>
      <flowInterruptionsHistogram nBins="0" >
      </flowInterruptionsHistogram>
    </Flow>
    <Flow flowId="3" timeFirstTxPacket="+16000001.0ns" timeFirstRxPacket="+16232468.0ns" timeLastTxPacket="+72000002.0ns" timeLastRxPacket="+76256499.0ns" delaySum="+16925842.0ns" jitterSum="+4024030.0ns" lastDelay="+4256497.0ns" txBytes="3272" rxBytes="3272" txPackets="5" rxPackets="5" lostPackets="0" timesForwarded="10">
      <delayHistogram nBins="5" >
        <bin index="0" start="0" width="0.001" count="1" />
        <bin index="3" start="0.003" width="0.001" count="1" />
        <bin index="4" start="0.004" width="0.001" count="3" />
      </delayHistogram>
      <jitterHistogram nBins="4" >
        <bin index="0" start="0" width="0.001" count="3" />
        <bin index="3" start="0.003" width="0.001" count="1" />
      </jitterHistogram>
      <packetSizeHistogram nBins="54" >
        <bin index="2" start="40" width="20" count="2" />
        <bin index="52" start="1040" width="20" count="1" />
        <bin index="53" start="1060" width="20" count="2" />
      </packetSizeHistogram>
      <flowInterruptionsHistogram nBins="0" >
      </flowInterruptionsHistogram>
    </Flow>
    <Flow flowId="4" timeFirstTxPacket="+16000001.0ns" timeFirstRxPacket="+16464468.0ns" timeLastTxPacket="+80000002.0ns" timeLastRxPacket="+84256499.0ns" delaySum="+13386264.0ns" jitterSum="+4384290.0ns" lastDelay="+4256497.0ns" txBytes="3272" rxBytes="3272" txPackets="5" rxPackets="5" lostPackets="0" timesForwarded="10">
      <delayHistogram nBins="5" >
        <bin index="0" start="0" width="0.001" count="2" />
        <bin index="4" start="0.004" width="0.001" count="3" />
      </delayHistogram>
      <jitterHistogram nBins="5" >
        <bin index="0" start="0" width="0.001" count="3" />
        <bin index="4" start="0.004" width="0.001" count="1" />
      </jitterHistogram>
      <packetSizeHistogram nBins="54" >
        <bin index="2" start="40" width="20" count="2" />
        <bin index="52" start="1040" width="20" count="1" />
        <bin index="53" start="1060" width="20" count="2" />
      </packetSizeHistogram>
      <flowInterruptionsHistogram nBins="0" >
      </flowInterruptionsHistogram>
    </Flow>
    <Flow flowId="5" timeFirstTxPacket="+16232468.0ns" timeFirstRxPacket="+16480967.0ns" timeLastTxPacket="+76256499.0ns" timeLastRxPacket="+76456902.0ns" delaySum="+849708.0ns" jitterSum="+48096.0ns" lastDelay="+200403.0ns" txBytes="204" rxBytes="204" txPackets="4" rxPackets="4" lostPackets="0" timesForwarded="8">
      <delayHistogram nBins="1" >
        <bin index="0" start="0" width="0.001" count="4" />
      </delayHistogram>
      <jitterHistogram nBins="1" >
        <bin index="0" start="0" width="0.001" count="3" />
      </jitterHistogram>
      <packetSizeHistogram nBins="4" >
        <bin index="2" start="40" width="20" count="3" />
        <bin index="3" start="60" width="20" count="1" />
      </packetSizeHistogram>
      <flowInterruptionsHistogram nBins="0" >
      </flowInterruptionsHistogram>
    </Flow>
    <Flow flowId="6" timeFirstTxPacket="+16464468.0ns" timeFirstRxPacket="+16712967.0ns" timeLastTxPacket="+84256499.0ns" timeLastRxPacket="+84456902.0ns" delaySum="+849708.0ns" jitterSum="+48096.0ns" lastDelay="+200403.0ns" txBytes="204" rxBytes="204" txPackets="4" rxPackets="4" lostPackets="0" timesForwarded="8">
      <delayHistogram nBins="1" >
        <bin index="0" start="0" width="0.001" count="4" />
      </delayHistogram>
      <jitterHistogram nBins="1" >
        <bin index="0" start="0" width="0.001" count="3" />
      </jitterHistogram>
      <packetSizeHistogram nBins="4" >
        <bin index="2" start="40" width="20" count="3" />
        <bin index="3" start="60" width="20" count="1" />
      </packetSizeHistogram>
      <flowInterruptionsHistogram nBins="0" >
      </flowInterruptionsHistogram>
    </Flow>
  </FlowStats>
  <Ipv4FlowClassifier>
    <Flow flowId="3" sourceAddress="10.1.3.4" destinationAddress="10.1.6.2" protocol="6" sourcePort="12777" destinationPort="1915">
      <Dscp value="0x0" packets="5" />
    </Flow>
    <Flow flowId="4" sourceAddress="10.1.3.4" destinationAddress="10.1.7.2" protocol="6" sourcePort="12793" destinationPort="48335">
      <Dscp value="0x0" packets="5" />
    </Flow>
    <Flow flowId="1" sourceAddress="10.1.3.4" destinationAddress="10.1.8.1" protocol="6" sourcePort="49153" destinationPort="999">
      <Dscp value="0x0" packets="7" />
    </Flow>
    <Flow flowId="5" sourceAddress="10.1.6.2" destinationAddress="10.1.3.4" protocol="6" sourcePort="1915" destinationPort="12777">
      <Dscp value="0x0" packets="4" />
    </Flow>
    <Flow flowId="6" sourceAddress="10.1.7.2" destinationAddress="10.1.3.4" protocol="6" sourcePort="48335" destinationPort="12793">
      <Dscp value="0x0" packets="4" />
    </Flow>
    <Flow flowId="2" sourceAddress="10.1.8.1" destinationAddress="10.1.3.4" protocol="6" sourcePort="999" destinationPort="49153">
      <Dscp value="0x0" packets="11" />
    </Flow>
  </Ipv4FlowClassifier>
  <Ipv6FlowClassifier>
  </Ipv6FlowClassifier>
  <FlowProbes>
    <FlowProbe index="0">
      <FlowStats  flowId="1" packets="7" bytes="5432" delayFromFirstProbeSum="+0.0ns" >
      </FlowStats>
      <FlowStats  flowId="2" packets="11" bytes="656" delayFromFirstProbeSum="+2781441.0ns" >
      </FlowStats>
      <FlowStats  flowId="3" packets="5" bytes="3272" delayFromFirstProbeSum="+0.0ns" >
      </FlowStats>
      <FlowStats  flowId="4" packets="5" bytes="3272" delayFromFirstProbeSum="+0.0ns" >
      </FlowStats>
      <FlowStats  flowId="5" packets="4" bytes="204" delayFromFirstProbeSum="+849708.0ns" >
      </FlowStats>
      <FlowStats  flowId="6" packets="4" bytes="204" delayFromFirstProbeSum="+849708.0ns" >
      </FlowStats>
    </FlowProbe>
    <FlowProbe index="1">
    </FlowProbe>
    <FlowProbe index="2">
      <FlowStats  flowId="1" packets="7" bytes="5432" delayFromFirstProbeSum="+21828043.0ns" >
      </FlowStats>
      <FlowStats  flowId="2" packets="11" bytes="656" delayFromFirstProbeSum="+0.0ns" >
      </FlowStats>
      <FlowStats  flowId="3" packets="5" bytes="3272" delayFromFirstProbeSum="+16925842.0ns" >
      </FlowStats>
      <FlowStats  flowId="4" packets="5" bytes="3272" delayFromFirstProbeSum="+13386264.0ns" >
      </FlowStats>
      <FlowStats  flowId="5" packets="4" bytes="204" delayFromFirstProbeSum="+0.0ns" >
      </FlowStats>
      <FlowStats  flowId="6" packets="4" bytes="204" delayFromFirstProbeSum="+0.0ns" >
      </FlowStats>
    </FlowProbe>
    <FlowProbe index="3">
    </FlowProbe>
    <FlowProbe index="4">
      <FlowStats  flowId="1" packets="7" bytes="5432" delayFromFirstProbeSum="+22250.0ns" >
      </FlowStats>
      <FlowStats  flowId="2" packets="11" bytes="656" delayFromFirstProbeSum="+2778723.0ns" >
      </FlowStats>
      <FlowStats  flowId="3" packets="5" bytes="3272" delayFromFirstProbeSum="+13130.0ns" >
      </FlowStats>
      <FlowStats  flowId="4" packets="5" bytes="3272" delayFromFirstProbeSum="+13362.0ns" >
      </FlowStats>
      <FlowStats  flowId="5" packets="4" bytes="204" delayFromFirstProbeSum="+848856.0ns" >
      </FlowStats>
      <FlowStats  flowId="6" packets="4" bytes="204" delayFromFirstProbeSum="+848856.0ns" >
      </FlowStats>
    </FlowProbe>
    <FlowProbe index="5">
    </FlowProbe>
    <FlowProbe index="6">
      <FlowStats  flowId="1" packets="2" bytes="2120" delayFromFirstProbeSum="+8504498.0ns" >
      </FlowStats>
      <FlowStats  flowId="2" packets="4" bytes="240" delayFromFirstProbeSum="+994.0ns" >
      </FlowStats>
      <FlowStats  flowId="3" packets="3" bytes="2172" delayFromFirstProbeSum="+8720716.0ns" >
      </FlowStats>
      <FlowStats  flowId="4" packets="2" bytes="96" delayFromFirstProbeSum="+632403.0ns" >
      </FlowStats>
      <FlowStats  flowId="5" packets="1" bytes="48" delayFromFirstProbeSum="+201.0ns" >
      </FlowStats>
      <FlowStats  flowId="6" packets="2" bytes="108" delayFromFirstProbeSum="+450.0ns" >
      </FlowStats>
    </FlowProbe>
    <FlowProbe index="7">
    </FlowProbe>
    <FlowProbe index="8">
      <FlowStats  flowId="1" packets="4" bytes="2236" delayFromFirstProbeSum="+8985445.0ns" >
      </FlowStats>
      <FlowStats  flowId="2" packets="3" bytes="176" delayFromFirstProbeSum="+730.0ns" >
      </FlowStats>
      <FlowStats  flowId="3" packets="2" bytes="1100" delayFromFirstProbeSum="+8191996.0ns" >
      </FlowStats>
      <FlowStats  flowId="4" packets="2" bytes="2120" delayFromFirstProbeSum="+8504498.0ns" >
      </FlowStats>
      <FlowStats  flowId="5" packets="1" bytes="60" delayFromFirstProbeSum="+249.0ns" >
      </FlowStats>
    </FlowProbe>
    <FlowProbe index="9">
    </FlowProbe>
    <FlowProbe index="10">
      <FlowStats  flowId="1" packets="1" bytes="1076" delayFromFirstProbeSum="+4316313.0ns" >
      </FlowStats>
      <FlowStats  flowId="2" packets="4" bytes="240" delayFromFirstProbeSum="+994.0ns" >
      </FlowStats>
      <FlowStats  flowId="4" packets="1" bytes="1056" delayFromFirstProbeSum="+4236233.0ns" >
      </FlowStats>
      <FlowStats  flowId="5" packets="2" bytes="96" delayFromFirstProbeSum="+402.0ns" >
      </FlowStats>
      <FlowStats  flowId="6" packets="2" bytes="96" delayFromFirstProbeSum="+402.0ns" >
      </FlowStats>
    </FlowProbe>
    <FlowProbe index="11">
    </FlowProbe>
  </FlowProbes>
</FlowMonitor>
